[
  {
    "loanId": "a1f377e9-1f56-4453-9886-432afabecd9a",
    "borrowerId": "3a99efb1-9db9-4566-94a0-457b4801b140",
    "borrowerWallet": "0xc90b37179bfe2cd9fa6658c47b4ca9e49412a416",
    "lenderId": "e02a009c-a3d1-4ab5-a6d3-e4ef908fb379",
    "lenderWallet": "0xf8950cc6a551f257764339fefa8e281fee6aaa68",
    "amount": 3000,
    "repaidAmount": 3000,
    "durationDays": 30,
    "status": "REPAID",
    "createdAt": "2026-04-04T07:06:52.335Z",
    "fundedAt": "2026-04-04T07:06:52.366Z",
    "dueAt": "2026-05-04T07:06:52.335Z",
    "defaultedAt": null,
    "repaidAt": "2026-04-04T07:06:52.444Z"
  },
  {
    "loanId": "686e6c30-e5ec-4bfd-bd0f-39cfc9e393b5",
    "borrowerId": "e02a009c-a3d1-4ab5-a6d3-e4ef908fb379",
    "borrowerWallet": "0xf8950cc6a551f257764339fefa8e281fee6aaa68",
    "lenderId": "3a99efb1-9db9-4566-94a0-457b4801b140",
    "lenderWallet": "0xc90b37179bfe2cd9fa6658c47b4ca9e49412a416",
    "amount": 2000,
    "repaidAmount": 0,
    "durationDays": 15,
    "status": "ACTIVE",
    "createdAt": "2026-04-04T07:06:52.481Z",
    "fundedAt": "2026-04-04T07:06:52.509Z",
    "dueAt": "2026-04-19T07:06:52.481Z",
    "defaultedAt": null,
    "repaidAt": null
  },
  {
    "loanId": "8db083fa-65f0-4221-aaec-9b11b019cdc4",
    "borrowerId": "aa135b30-de3e-4c80-81f3-20d631372a67",
    "borrowerWallet": "0x006afe24f09450f7c0336b71268628d871e37d6c",
    "lenderId": null,
    "lenderWallet": null,
    "amount": 1500,
    "repaidAmount": 0,
    "durationDays": 7,
    "status": "PENDING",
    "createdAt": "2026-04-04T07:06:52.572Z",
    "fundedAt": null,
    "dueAt": "2026-04-11T07:06:52.572Z",
    "defaultedAt": null,
    "repaidAt": null
  },
  {
    "loanId": "efd3ab86-ba99-42b1-95cb-a442e9368412",
    "borrowerId": "3a99efb1-9db9-4566-94a0-457b4801b140",
    "borrowerWallet": "0xc90b37179bfe2cd9fa6658c47b4ca9e49412a416",
    "lenderId": null,
    "lenderWallet": null,
    "amount": 5000,
    "repaidAmount": 0,
    "durationDays": 60,
    "status": "PENDING",
    "createdAt": "2026-04-04T07:06:52.585Z",
    "fundedAt": null,
    "dueAt": "2026-06-03T07:06:52.585Z",
    "defaultedAt": null,
    "repaidAt": null
  },
  {
    "loanId": "cb509ea2-f36d-4ad2-9fe8-4dee71ed5a11",
    "borrowerId": "7f478c14-3da8-4c0b-a7f0-6cd684bcaca4",
    "borrowerWallet": "0x8c22d639508109923f625cb088f95bfff63ad755",
    "lenderId": null,
    "lenderWallet": null,
    "amount": 1000,
    "repaidAmount": 0,
    "durationDays": 30,
    "status": "PENDING",
    "createdAt": "2026-04-04T07:27:17.807Z",
    "fundedAt": null,
    "dueAt": "2026-05-04T07:27:17.807Z",
    "defaultedAt": null,
    "repaidAt": null
  },
  {
    "loanId": "b8e6d54a-a877-4ac2-bfa8-3154bb803e2b",
    "borrowerId": "e85a2e45-ed55-4f7a-8200-fdc07eeb6cf6",
    "borrowerWallet": "0xacce0901da2ef5f7a588ad7367f08e41b8706693",
    "lenderId": null,
    "lenderWallet": null,
    "amount": 1000,
    "repaidAmount": 0,
    "durationDays": 30,
    "status": "PENDING",
    "createdAt": "2026-04-04T07:46:40.443Z",
    "fundedAt": null,
    "dueAt": "2026-05-04T07:46:40.443Z",
    "defaultedAt": null,
    "repaidAt": null
  },
  {
    "loanId": "a8f6f2ca-7a88-4556-b8bb-7e27f3014191",
    "borrowerId": "e85a2e45-ed55-4f7a-8200-fdc07eeb6cf6",
    "borrowerWallet": "0xacce0901da2ef5f7a588ad7367f08e41b8706693",
    "lenderId": null,
    "lenderWallet": null,
    "amount": 3000,
    "repaidAmount": 0,
    "durationDays": 30,
    "status": "PENDING",
    "createdAt": "2026-04-04T08:03:49.986Z",
    "fundedAt": null,
    "dueAt": "2026-05-04T08:03:49.986Z",
    "defaultedAt": null,
    "repaidAt": null
  }
]